README.txt
setup.cfg
setup.py
virtualkeyring.py
virtualkeyring.egg-info/PKG-INFO
virtualkeyring.egg-info/SOURCES.txt
virtualkeyring.egg-info/dependency_links.txt
virtualkeyring.egg-info/entry_points.txt
virtualkeyring.egg-info/requires.txt
virtualkeyring.egg-info/top_level.txt
virtualkeyring.egg-info/zip-safe