Metadata-Version: 1.1
Name: virtualkeyring
Version: 1.6
Summary: Strong domain-specific passwords generator
Home-page: http://bitbucket.org/ogrisel/virtualkeyring
Author: Olivier Grisel
Author-email: olivier.grisel@ensta.org
License: GPLv3
Keywords: hash sha1 password generator keyring master
Platform: UNKNOWN
Classifier: Development Status :: 5 - Production/Stable
Classifier: Environment :: Console
Classifier: Intended Audience :: Information Technology
Classifier: License :: OSI Approved :: GNU General Public License (GPL)
Classifier: Operating System :: OS Independent
Classifier: Programming Language :: Python
